README.rst
setup.py
roca_gui/__init__.py
roca_gui/detector.py
roca_gui.egg-info/PKG-INFO
roca_gui.egg-info/SOURCES.txt
roca_gui.egg-info/dependency_links.txt
roca_gui.egg-info/entry_points.txt
roca_gui.egg-info/not-zip-safe
roca_gui.egg-info/requires.txt
roca_gui.egg-info/top_level.txt
roca_gui/test/ICAO.py
roca_gui/test/__init__.py
roca_gui/test/apk_spider.py
roca_gui/test/convert-dnskey.py
roca_gui/test/process_crl.py
roca_gui/test/process_csv_key.py
roca_gui/test/process_ip_tls.py