Metadata-Version: 1.2
Name: roca-gui
Version: 4.3
Summary: vunerable rsa keys detector
Home-page: UNKNOWN
Author: Cao Pei
Author-email: 970379828@qq.com
License: BSD
Platform: UNKNOWN
Classifier: Development Status :: 3 - Alpha
Classifier: Environment :: Web Environment
Classifier: Intended Audience :: Developers
Classifier: License :: OSI Approved :: BSD License
Classifier: Operating System :: OS Independent
Classifier: Programming Language :: Python
Classifier: Framework :: Django
Requires-Python: >=2.7.10,!=3.0.*,!=3.1.*,!=3.2.*,!=3.3.*
